dash_calendar_timeline/DashCalendarTimeline.py
dash_calendar_timeline/__init__.py
dash_calendar_timeline/_imports_.py
dash_calendar_timeline/dash_calendar_timeline.min.js
dash_calendar_timeline/dash_calendar_timeline.min.js.map
dash_calendar_timeline/metadata.json
dash_calendar_timeline/package-info.json
dash_calendar_timeline-1.0.2.dist-info/licenses/LICENSE
dash_calendar_timeline-1.0.2.dist-info/METADATA
dash_calendar_timeline-1.0.2.dist-info/WHEEL
dash_calendar_timeline-1.0.2.dist-info/top_level.txt
dash_calendar_timeline-1.0.2.dist-info/RECORD
