Metadata-Version: 2.4
Name: dash_calendar_timeline
Version: 1.0.2
Summary: A custom component for rendering react-calendar-timeline in Dash Apps.
Author: Waleed Malik <zenalytiks@gmail.com>
License: MIT
Classifier: Framework :: Dash
License-File: LICENSE
Dynamic: author
Dynamic: classifier
Dynamic: description
Dynamic: description-content-type
Dynamic: license
Dynamic: license-file
Dynamic: summary
